pycommonregex/__init__.py
pycommonregex/pycommonregex.py
pycommonregex-0.1.2.dist-info/METADATA
pycommonregex-0.1.2.dist-info/WHEEL
pycommonregex-0.1.2.dist-info/LICENSE
pycommonregex-0.1.2.dist-info/RECORD
