Metadata-Version: 2.1
Name: pycommonregex
Version: 0.1.2
Summary: A Python package for common regular expressions.
Home-page: https://github.com/fadedreams/pycommonregex
License: MIT
Keywords: regex,utilities
Author: fadedreams7
Author-email: fadedreams7@gmail.com
Requires-Python: >=3.8,<4.0
Classifier: Environment :: Console
Classifier: License :: OSI Approved :: MIT License
Classifier: Operating System :: OS Independent
Classifier: Programming Language :: Python :: 3
Classifier: Programming Language :: Python :: 3.8
Classifier: Programming Language :: Python :: 3.9
Classifier: Programming Language :: Python :: 3.10
Classifier: Programming Language :: Python :: 3.11
Classifier: Programming Language :: Python :: 3
Classifier: Topic :: Utilities
Requires-Dist: pytest (>=7.2.1,<8.0.0)
Project-URL: Repository, https://github.com/fadedreams/pycommonregex
